polym/__init__.py
polym/polynomial.py
polym-0.1.2.dist-info/METADATA
polym-0.1.2.dist-info/WHEEL
polym-0.1.2.dist-info/RECORD
